{
  "state": "North Carolina",
  "abbr": "NC",
  "interstates": {
    "I-26": {
      "maxMM": 70,
      "stops": [
        {
          "mm": 6,
          "exit": "6",
          "name": "North Carolina Welcome Center (eastbound)",
          "brand": "State",
          "type": "rest_area",
          "city": "Mars Hill (Madison County)",
          "approx": true,
          "parking": 15
        },
        {
          "mm": 44,
          "exit": "44",
          "name": "FleetPro Truck Center",
          "brand": "Independent",
          "type": "repair",
          "city": "Fletcher",
          "approx": true,
          "notes": "Family-owned heavy truck and trailer shop at 4989 Hendersonville Rd (US-25) near I-26 exit 44 (Fletcher/Mountain Home); engine diagnostics, AC, suspension/brakes, DOT inspections, emergency roadside; M-F 8am-10:30pm"
        },
        {
          "mm": 46,
          "exit": "46",
          "name": "Weigh Station (both directions)",
          "brand": "State",
          "type": "weigh_station",
          "city": "Hendersonville",
          "approx": true,
          "notes": "SHP Hendersonville scales north of US-64, two fixed scales; PrePass"
        },
        {
          "mm": 68,
          "exit": "68",
          "name": "North Carolina Welcome Center (westbound)",
          "brand": "State",
          "type": "rest_area",
          "city": "Columbus/Tryon",
          "approx": true,
          "notes": "Serves westbound entering from SC; truck parking",
          "parking": 20
        }
      ]
    },
    "I-40": {
      "maxMM": 420,
      "stops": [
        {
          "mm": 10,
          "exit": "10",
          "name": "North Carolina Welcome Center (eastbound)",
          "brand": "State",
          "type": "rest_area",
          "city": "Waynesville (Haywood County)",
          "approx": true,
          "notes": "Serves eastbound entering from TN through Pigeon River Gorge; truck parking",
          "parking": 20
        },
        {
          "mm": 37,
          "exit": "37",
          "name": "Pilot Travel Center",
          "brand": "Pilot",
          "type": "truck_stop",
          "city": "Candler (Asheville west)",
          "approx": true,
          "notes": "",
          "parking": 85
        },
        {
          "mm": 86,
          "exit": "86",
          "name": "Love's Travel Stop",
          "brand": "Love's",
          "type": "truck_stop",
          "city": "Marion",
          "approx": true,
          "notes": "NC-226. Note: I-40 shares I-85 mileposts on the Greensboro-Hillsborough overlap; see I-85 for Mebane stops",
          "parking": 85
        },
        {
          "mm": 112,
          "exit": "112",
          "name": "Burke County Rest Area (both directions)",
          "brand": "State",
          "type": "rest_area",
          "city": "Valdese",
          "approx": true,
          "parking": 25
        },
        {
          "mm": 133,
          "exit": "133",
          "name": "Sheetz Conover",
          "brand": "Independent",
          "type": "truck_stop",
          "city": "Conover",
          "approx": false,
          "notes": "Sheetz truck-diesel format, opened Feb 2026; 7 high-flow diesel lanes, 46 free truck spaces",
          "parking": 46
        },
        {
          "mm": 177,
          "exit": "177",
          "name": "Iredell County Rest Area (both directions)",
          "brand": "State",
          "type": "rest_area",
          "city": "Statesville",
          "approx": true,
          "parking": 30
        },
        {
          "mm": 325,
          "exit": "325",
          "name": "Rest Area (both directions)",
          "brand": "State",
          "type": "rest_area",
          "city": "Benson (Johnston County)",
          "approx": true,
          "notes": "Truck parking; serves EB and WB",
          "parking": 25
        },
        {
          "mm": 364,
          "exit": "364",
          "name": "Duplin County Rest Area (both directions)",
          "brand": "State",
          "type": "rest_area",
          "city": "Warsaw",
          "approx": true,
          "parking": 25
        }
      ]
    },
    "I-73": {
      "maxMM": 135,
      "stops": []
    },
    "I-74": {
      "maxMM": 210,
      "stops": []
    },
    "I-77": {
      "maxMM": 105,
      "stops": [
        {
          "mm": 82,
          "exit": "82",
          "name": "Speedway Travel Plaza (former WilcoHess)",
          "brand": "Independent",
          "type": "truck_stop",
          "city": "Jonesville (Elkin)",
          "approx": true,
          "notes": "Legacy WilcoHess truck stop, now Speedway",
          "parking": 60
        },
        {
          "mm": 102,
          "exit": "102",
          "name": "Weigh Station (both directions)",
          "brand": "State",
          "type": "weigh_station",
          "city": "Mount Airy",
          "approx": true,
          "notes": "SHP Mount Airy scales about 3 mi south of VA line, two fixed scales; PrePass"
        },
        {
          "mm": 103,
          "exit": "103",
          "name": "North Carolina Welcome Center (southbound)",
          "brand": "State",
          "type": "rest_area",
          "city": "Dobson area (Surry County)",
          "approx": true,
          "notes": "Serves southbound entering from VA off Fancy Gap; truck parking",
          "parking": 20
        }
      ]
    },
    "I-85": {
      "maxMM": 234,
      "stops": [
        {
          "mm": 2,
          "exit": "2",
          "name": "North Carolina Welcome Center (northbound)",
          "brand": "State",
          "type": "rest_area",
          "city": "Grover (Cleveland County)",
          "approx": true,
          "notes": "Serves northbound entering from SC; truck parking",
          "parking": 20
        },
        {
          "mm": 5,
          "exit": "5",
          "name": "Love's Travel Stop",
          "brand": "Love's",
          "type": "truck_stop",
          "city": "Kings Mountain",
          "approx": true,
          "notes": "Dixon School Rd",
          "parking": 85
        },
        {
          "mm": 28,
          "exit": "28",
          "name": "Weigh Station (both directions)",
          "brand": "State",
          "type": "weigh_station",
          "city": "Charlotte (Mount Holly)",
          "approx": true,
          "notes": "SHP Charlotte scales, four fixed scales, NB at MM 28 east of NC-273; PrePass"
        },
        {
          "mm": 71,
          "exit": "71",
          "name": "Speedway Travel Plaza (former WilcoHess)",
          "brand": "Independent",
          "type": "truck_stop",
          "city": "Salisbury",
          "approx": true,
          "notes": "Peeler Rd; legacy WilcoHess site",
          "parking": 60
        },
        {
          "mm": 124,
          "exit": "124",
          "name": "TA Greensboro",
          "brand": "TA",
          "type": "truck_stop",
          "city": "Greensboro",
          "approx": true,
          "notes": "S Elm-Eugene St",
          "parking": 190
        },
        {
          "mm": 150,
          "exit": "150",
          "name": "Blue Beacon Truck Wash",
          "brand": "Independent",
          "type": "truck_wash",
          "city": "Haw River",
          "approx": false,
          "notes": "Jimmie Kerr Rd on I-40/I-85 overlap; across from Flying J"
        },
        {
          "mm": 153,
          "exit": "153",
          "name": "Speedway Travel Plaza (former WilcoHess)",
          "brand": "Independent",
          "type": "truck_stop",
          "city": "Mebane",
          "approx": true,
          "notes": "On I-85/I-40 overlap; legacy WilcoHess site",
          "parking": 60
        },
        {
          "mm": 160,
          "exit": "160",
          "name": "Weigh Station (both directions)",
          "brand": "State",
          "type": "weigh_station",
          "city": "Efland (Hillsborough)",
          "approx": true,
          "notes": "SHP Hillsborough scales on I-40/I-85 overlap, four fixed scales plus ramp/highway weigh-in-motion; PrePass"
        },
        {
          "mm": 191,
          "exit": "191",
          "name": "Love's Travel Stop",
          "brand": "Love's",
          "type": "truck_stop",
          "city": "Butner",
          "approx": true,
          "notes": "US-15",
          "parking": 85
        },
        {
          "mm": 231,
          "exit": "231",
          "name": "North Carolina Welcome Center (southbound)",
          "brand": "State",
          "type": "rest_area",
          "city": "Wise (Warren County)",
          "approx": true,
          "notes": "Serves southbound entering from VA; truck parking",
          "parking": 20
        }
      ]
    },
    "I-95": {
      "maxMM": 181,
      "stops": [
        {
          "mm": 5,
          "exit": "5",
          "name": "North Carolina Welcome Center (northbound)",
          "brand": "State",
          "type": "rest_area",
          "city": "Rowland",
          "approx": true,
          "notes": "Serves northbound entering from SC; truck parking",
          "parking": 20
        },
        {
          "mm": 24,
          "exit": "24",
          "name": "Weigh Station (both directions)",
          "brand": "State",
          "type": "weigh_station",
          "city": "Lumberton",
          "approx": false,
          "notes": "SHP Lumberton scales, MM 24, two fixed scales; PrePass"
        },
        {
          "mm": 33,
          "exit": "33",
          "name": "Love's Travel Stop",
          "brand": "Love's",
          "type": "truck_stop",
          "city": "St. Pauls",
          "approx": true,
          "notes": "",
          "parking": 85
        },
        {
          "mm": 41,
          "exit": "41",
          "name": "Sheetz Hope Mills",
          "brand": "Independent",
          "type": "truck_stop",
          "city": "Hope Mills",
          "approx": true,
          "notes": "Sheetz truck-diesel format, opened Feb 2025; 7 diesel lanes, 41 free overnight truck spaces",
          "parking": 41
        },
        {
          "mm": 49,
          "exit": "49",
          "name": "Cumberland County Rest Area (both directions)",
          "brand": "State",
          "type": "rest_area",
          "city": "Wade (Fayetteville)",
          "approx": true,
          "parking": 30
        },
        {
          "mm": 95,
          "exit": "95",
          "name": "Sleep Inn & Suites Smithfield",
          "brand": "Sleep Inn",
          "type": "hotel",
          "city": "Smithfield",
          "approx": false,
          "notes": "Truck parking verified: booking listings show RV, bus, and truck parking; 270 N Equity Dr at Exit 95"
        },
        {
          "mm": 106,
          "exit": "106",
          "name": "Kenly 95 Truckstop",
          "brand": "Independent",
          "type": "truck_stop",
          "city": "Kenly",
          "approx": false,
          "notes": "Large full-service independent (Petro-affiliated); truck wash, restaurant",
          "parking": 200
        },
        {
          "mm": 106,
          "exit": "106",
          "name": "Blue Beacon Truck Wash",
          "brand": "Independent",
          "type": "truck_wash",
          "city": "Kenly",
          "approx": false,
          "notes": "At Flying J Travel Center"
        },
        {
          "mm": 106,
          "exit": "106",
          "name": "Kenly 95 Truck Wash (Truckomat)",
          "brand": "Independent",
          "type": "truck_wash",
          "city": "Kenly",
          "approx": false,
          "notes": "At Kenly 95 Truckstop; 24-hour hand-brushed wash"
        },
        {
          "mm": 106,
          "exit": "106",
          "name": "Motel 6 Kenly",
          "brand": "Motel 6",
          "type": "hotel",
          "city": "Kenly",
          "approx": false,
          "notes": "Truck parking verified: listings show free self-parking for cars, trucks, and trailers; at Exit 106 adjacent to Kenly 95 Petro truck stop"
        },
        {
          "mm": 107,
          "exit": "107",
          "name": "Big Boy's Truck Stop",
          "brand": "AmBest",
          "type": "truck_stop",
          "city": "Kenly",
          "approx": true,
          "notes": "Independent AmBest member",
          "parking": 60
        },
        {
          "mm": 145,
          "exit": "145",
          "name": "TA Battleboro (Gold Rock)",
          "brand": "TA",
          "type": "truck_stop",
          "city": "Battleboro (Rocky Mount)",
          "approx": false,
          "notes": "NC-4, Gold Rock",
          "parking": 190
        },
        {
          "mm": 151,
          "exit": "151",
          "name": "Weigh Station (both directions)",
          "brand": "State",
          "type": "weigh_station",
          "city": "Enfield (Halifax County)",
          "approx": false,
          "notes": "SHP Halifax scales, NB and SB at MM 151, two fixed scales each; PrePass"
        },
        {
          "mm": 154,
          "exit": "154",
          "name": "Love's Travel Stop",
          "brand": "Love's",
          "type": "truck_stop",
          "city": "Enfield",
          "approx": true,
          "notes": "NC-481",
          "parking": 85
        },
        {
          "mm": 171,
          "exit": "171",
          "name": "Pilot Travel Center",
          "brand": "Pilot",
          "type": "truck_stop",
          "city": "Roanoke Rapids",
          "approx": true,
          "notes": "NC-125",
          "parking": 85
        },
        {
          "mm": 176,
          "exit": "176",
          "name": "North Carolina Welcome Center (southbound)",
          "brand": "State",
          "type": "rest_area",
          "city": "Roanoke Rapids (Northampton County)",
          "approx": true,
          "notes": "Serves southbound entering from VA; truck parking",
          "parking": 20
        }
      ]
    }
  }
}
