{
  "state": "Oregon",
  "abbr": "OR",
  "interstates": {
    "I-5": {
      "maxMM": 308,
      "stops": [
        {"mm": 24, "exit": "24", "name": "Petro Stopping Center", "brand": "Petro", "type": "truck_stop", "city": "Phoenix", "approx": false, "notes": "Fern Valley Rd, Medford/Ashland area"},
        {"mm": 33, "exit": "33", "name": "Pilot Travel Center", "brand": "Pilot", "type": "truck_stop", "city": "Central Point", "approx": false, "notes": "Former Witham Truck Stop"},
        {"mm": 99, "exit": "99", "name": "Seven Feathers Truck & Travel Center", "brand": "Independent", "type": "truck_stop", "city": "Canyonville", "approx": false, "notes": "Cow Creek tribal travel center at Seven Feathers Casino"},
        {"mm": 143, "exit": "", "name": "Oak Grove Rest Area", "brand": "State", "type": "rest_area", "city": "Rice Hill area", "approx": true, "notes": "Serves both directions; truck parking"},
        {"mm": 148, "exit": "148", "name": "Pilot Travel Center", "brand": "Pilot", "type": "truck_stop", "city": "Rice Hill", "approx": false, "notes": ""},
        {"mm": 199, "exit": "199", "name": "TA Coburg", "brand": "TA", "type": "truck_stop", "city": "Coburg", "approx": false, "notes": "North of Eugene"},
        {"mm": 199, "exit": "199", "name": "Pilot Travel Center", "brand": "Pilot", "type": "truck_stop", "city": "Coburg", "approx": false, "notes": ""},
        {"mm": 209, "exit": "209", "name": "Pilot Travel Center", "brand": "Pilot", "type": "truck_stop", "city": "Halsey", "approx": false, "notes": "Halsey/Brownsville exit"},
        {"mm": 233, "exit": "233", "name": "Love's Travel Stop", "brand": "Love's", "type": "truck_stop", "city": "Millersburg", "approx": true, "notes": "Albany area"},
        {"mm": 263, "exit": "263", "name": "Pilot Travel Center", "brand": "Pilot", "type": "truck_stop", "city": "Brooks", "approx": false, "notes": "Salem north (Brooks)"},
        {"mm": 278, "exit": "278", "name": "TA Aurora", "brand": "TA", "type": "truck_stop", "city": "Aurora", "approx": false, "notes": "Ehlen Rd, Aurora/Donald"},
        {"mm": 281, "exit": "", "name": "French Prairie (NB) / Baldock (SB) Rest Areas", "brand": "State", "type": "rest_area", "city": "Wilsonville area", "approx": true, "notes": "Paired rest areas, large truck parking"},
        {"mm": 282, "exit": "282", "name": "Love's Travel Stop", "brand": "Love's", "type": "truck_stop", "city": "Aurora", "approx": true, "notes": "Canby/Aurora exit"},
        {"mm": 307, "exit": "307", "name": "Jubitz Travel Center", "brand": "Independent", "type": "truck_stop", "city": "Portland", "approx": false, "notes": "Famous independent; full-service with cinema, lounge, Ponderosa"}
      ]
    },
    "I-82": {
      "maxMM": 11,
      "stops": []
    },
    "I-84": {
      "maxMM": 378,
      "stops": [
        {"mm": 17, "exit": "17", "name": "TA Portland", "brand": "TA", "type": "truck_stop", "city": "Troutdale", "approx": false, "notes": ""},
        {"mm": 17, "exit": "17", "name": "Love's Travel Stop", "brand": "Love's", "type": "truck_stop", "city": "Troutdale", "approx": false, "notes": ""},
        {"mm": 73, "exit": "", "name": "Memaloose Rest Area", "brand": "State", "type": "rest_area", "city": "Mosier", "approx": false, "notes": "Serves both directions; truck parking, Columbia Gorge"},
        {"mm": 104, "exit": "104", "name": "Pilot Travel Center", "brand": "Pilot", "type": "truck_stop", "city": "Biggs Junction", "approx": false, "notes": "US-97 junction at Columbia River"},
        {"mm": 164, "exit": "164", "name": "Love's Travel Stop", "brand": "Love's", "type": "truck_stop", "city": "Boardman", "approx": true, "notes": ""},
        {"mm": 164, "exit": "164", "name": "Pilot Travel Center", "brand": "Pilot", "type": "truck_stop", "city": "Boardman", "approx": true, "notes": ""},
        {"mm": 188, "exit": "188", "name": "Space Age Travel Center", "brand": "Independent", "type": "truck_stop", "city": "Hermiston", "approx": true, "notes": "Hermiston/Stanfield exit, US-395"},
        {"mm": 188, "exit": "188", "name": "Pilot Travel Center", "brand": "Pilot", "type": "truck_stop", "city": "Stanfield", "approx": true, "notes": ""},
        {"mm": 216, "exit": "216", "name": "Arrowhead Travel Plaza", "brand": "Independent", "type": "truck_stop", "city": "Pendleton", "approx": false, "notes": "Umatilla tribal plaza at Wildhorse Resort, Mission"},
        {"mm": 228, "exit": "", "name": "Deadman Pass Rest Areas", "brand": "State", "type": "rest_area", "city": "Emigrant Hill", "approx": false, "notes": "Both directions; chain-up truck parking atop Cabbage Hill"},
        {"mm": 265, "exit": "265", "name": "Flying J Travel Center", "brand": "Flying J", "type": "truck_stop", "city": "La Grande", "approx": false, "notes": ""},
        {"mm": 304, "exit": "304", "name": "Pilot Travel Center", "brand": "Pilot", "type": "truck_stop", "city": "Baker City", "approx": false, "notes": "Campbell St"},
        {"mm": 335, "exit": "", "name": "Weatherby Rest Area", "brand": "State", "type": "rest_area", "city": "Weatherby", "approx": false, "notes": "Serves both directions; truck parking"},
        {"mm": 376, "exit": "376", "name": "Pilot Travel Center", "brand": "Pilot", "type": "truck_stop", "city": "Ontario", "approx": true, "notes": "Near Idaho line"},
        {"mm": 376, "exit": "376", "name": "Love's Travel Stop", "brand": "Love's", "type": "truck_stop", "city": "Ontario", "approx": true, "notes": ""}
      ]
    }
  }
}
